FX_Manager-1.0.16.data/scripts/create_fx_proj.py
FX_Manager-1.0.16.data/scripts/fx_data_collector.py
FX_Manager-1.0.16.data/scripts/fx_pp.py
FX_Manager-1.0.16.data/scripts/run_fx_hist_sim.py
FX_Manager-1.0.16.data/scripts/run_fx_live_sim.py
FX_Manager-1.0.16.data/scripts/run_fx_opt_test.py
fxmanager/__init__.py
fxmanager/_metadata.py
fxmanager/basic/__init__.py
fxmanager/basic/account.py
fxmanager/basic/util.py
fxmanager/dwx/DWX_ZMQ_Execution.py
fxmanager/dwx/DWX_ZMQ_Reporting.py
fxmanager/dwx/DWX_ZMQ_Strategy.py
fxmanager/dwx/DWX_ZeroMQ_Connector_v2_0_1_RC8.py
fxmanager/dwx/__init__.py
fxmanager/dwx/prices_subscriptions.py
fxmanager/dwx/rates_historic.py
fxmanager/optimization/__init__.py
fxmanager/optimization/eq_weight_optimizer.py
fxmanager/optimization/eqw_optimization_test.py
fxmanager/optimization/w_optimization_test.py
fxmanager/optimization/weight_optimizer.py
fxmanager/simulation/__init__.py
fxmanager/simulation/historic.py
fxmanager/simulation/live.py
fxmanager/strategies/__init__.py
fxmanager/strategies/naieve_momentum.py
fxmanager/strategies/template.py
FX_Manager-1.0.16.dist-info/LICENSE
FX_Manager-1.0.16.dist-info/METADATA
FX_Manager-1.0.16.dist-info/WHEEL
FX_Manager-1.0.16.dist-info/top_level.txt
FX_Manager-1.0.16.dist-info/RECORD
