Metadata-Version: 2.1
Name: FX-Manager
Version: 1.0.16
Summary: Python package for developing and testing forex algorithmic trading strategies.
Home-page: https://github.com/AbdullahBahi/fxmanager
Author: Abdullah Bahi
Author-email: abdullahbahi@icloud.com
License: UNKNOWN
Keywords: forex,forex trading,algorethmic trading,backtesting
Platform: UNKNOWN
Classifier: Development Status :: 3 - Alpha
Classifier: Intended Audience :: Developers
Classifier: Topic :: Software Development :: Build Tools
Classifier: License :: OSI Approved :: GNU General Public License (GPL)
Classifier: Programming Language :: Python :: 3
Classifier: Operating System :: OS Independent
Requires-Python: >=3.7
License-File: LICENSE
Requires-Dist: zmq
Requires-Dist: pandas (>=0.25.1)
Requires-Dist: numpy (>=1.16.5)
Requires-Dist: matplotlib (>=3.1.1)
